topsis/__init__.py
topsis/topsis.py
102216005_Topsis-1.0.1.dist-info/METADATA
102216005_Topsis-1.0.1.dist-info/WHEEL
102216005_Topsis-1.0.1.dist-info/entry_points.txt
102216005_Topsis-1.0.1.dist-info/top_level.txt
102216005_Topsis-1.0.1.dist-info/RECORD
