Metadata-Version: 2.2
Name: 102216005_Topsis
Version: 1.0.1
Summary: A Python implementation of the TOPSIS decision-making method
Home-page: https://github.com/Reetinder932/topsis
Author: Reetinder Singh
Author-email: your.email@example.com
Classifier: Programming Language :: Python :: 3
Classifier: License :: OSI Approved :: MIT License
Classifier: Operating System :: OS Independent
Requires-Python: >=3.6
Requires-Dist: numpy
Requires-Dist: pandas
Dynamic: author
Dynamic: author-email
Dynamic: classifier
Dynamic: description
Dynamic: description-content-type
Dynamic: home-page
Dynamic: requires-dist
Dynamic: requires-python
Dynamic: summary
